PySimpleAutomata/AFW.py
PySimpleAutomata/DFA.py
PySimpleAutomata/NFA.py
PySimpleAutomata/__init__.py
PySimpleAutomata/automata_IO.py
PySimpleAutomata-0.5.0.data/data/LICENSE
PySimpleAutomata-0.5.0.dist-info/DESCRIPTION.rst
PySimpleAutomata-0.5.0.dist-info/METADATA
PySimpleAutomata-0.5.0.dist-info/RECORD
PySimpleAutomata-0.5.0.dist-info/WHEEL
PySimpleAutomata-0.5.0.dist-info/metadata.json
PySimpleAutomata-0.5.0.dist-info/top_level.txt
