Metadata-Version: 2.0
Name: PySimpleAutomata
Version: 0.5.0
Summary: Python library to manage DFA, NFA and AFW automata
Home-page: https://github.com/Oneiroe/PySimpleAutomata
Author: Alessio Cecconi
Author-email: alessio.cecconi.1991@gmail.com
License: MIT License
Requires-Dist: graphviz
Requires-Dist: pydot
